<Alloy>
    <ScrollView class="wfill hfill vert" backgroundImage="/images/home_background.jpg" contentHeight="Ti.UI.SIZE" contentWidth="Ti.UI.FILL">
    	<TableView class="wfill hfill padding box">
    		<TableViewRow hasChild="true" class="horz">
    			<View class="hsize padding vert" width="80">
    				<Label>June 2015</Label>
    				<Label class="font_big">FRI 6</Label>
    			</View>
    			<View height="80" width="1" backgroundColor="#dfe0e4"></View>
	    		<View class="wfill hsize padding vert">
	    			<Label class="font_big">Math</Label>
	    			<Label>Teacher: Mohama Ali</Label>
	    			<Label class="font_light_grey">Due date: 6, June 2015</Label>
    			</View>
    		</TableViewRow>
    		<TableViewRow hasChild="true" class="horz">
    			<View class="hsize padding vert" width="80">
    				<Label>June 2015</Label>
    				<Label class="font_big">FRI 6</Label>
    			</View>
    			<View height="80" width="1" backgroundColor="#dfe0e4"></View>
	    		<View class="wfill hsize padding vert">
	    			<Label class="font_big">English</Label>
	    			<Label>Teacher: Mohama Ali</Label>
	    			<Label class="font_light_grey">Due date: 6, June 2015</Label>
    			</View>
    		</TableViewRow>
    		<TableViewRow hasChild="true" class="horz">
    			<View class="hsize padding vert" width="80">
    				<Label>June 2015</Label>
    				<Label class="font_big">FRI 6</Label>
    			</View>
    			<View height="80" width="1" backgroundColor="#dfe0e4"></View>
	    		<View class="wfill hsize padding vert">
	    			<Label class="font_big">Art</Label>
	    			<Label>Teacher: Mohama Ali</Label>
	    			<Label class="font_light_grey">Due date: 6, June 2015</Label>
    			</View>
    		</TableViewRow>
    	</TableView>
	</ScrollView>
</Alloy>